easyTDV/Deploy.py
easyTDV/DeploymentNomenclature.py
easyTDV/Train.py
easyTDV/TrainNomenclature.py
easyTDV/UserAwsAuth.py
easyTDV/Vizualisation.py
easyTDV/VizualisationNomenclature.py
easyTDV/__init__.py
easyTDV/deployment_helper.py
easyTDV/main.py
easyTDV/main_test_sans_easyTDV.py
easyTDV/train_helper.py
easyTDV/vizualisation_helper.py
easyTDV/resources/clf_deployment_stack.json
easyTDV/resources/clf_train_stack.json
easyTDV/resources/clf_vizualisation_stack.json
easyTDV/resources/lambda_deployment.zip
easyTDV/resources/lambda_train.zip
easyTDV/resources/layers/python.zip
easyTDV-1.2.5.dist-info/METADATA
easyTDV-1.2.5.dist-info/WHEEL
easyTDV-1.2.5.dist-info/top_level.txt
easyTDV-1.2.5.dist-info/RECORD
